makefile_parser
