Metadata-Version: 1.1
Name: mksearch
Version: 1.0.2
Summary: Recursively search makefiles for a value and output json parseable list
Home-page: https://github.com/itow0001/mksearch
Author: Ian Itow
Author-email: itow0001@gmail.com
License: MIT
Platform: UNKNOWN
Classifier: Topic :: Software Development :: Build Tools
Classifier: Programming Language :: Python :: 2.7
